adder.v
/**************************************
* Module: adder
* Date:2014-10-09  
* Author: Luís     
*
* Description: Somador simples
***************************************/
module  adder(Cout, Sum, A, B, Cin);
    output Cout, Sum;
    input A, B, Cin;
    
    and I1 (i1_out, A, B);
    xor I2 (i2_out, A, B);
    
    and J1 (j1_out, i2_out, Cin);
    xor J2 (Sum, i2_out, Cin);
    
    or K1 (Cout, i1_out, j1_out);
endmodule

test.v
/**************************************
* Module: test
* Date:2014-10-09  
* Author: Luís     
*
* Description: Módulo para teste
***************************************/
module test;

  /* Make a reset that pulses once. */
  reg a = 0, b = 0, cin = 0;

    initial begin
        $dumpfile("test.vcd");
        $dumpvars(0,test);
        # 1 a = 0; b = 0; cin = 0; 
        # 1 a = 0; b = 0; cin = 1; 
        # 1 a = 0; b = 1; cin = 0;
        # 1 a = 0; b = 1; cin = 1;
        # 1 a = 1; b = 0; cin = 0;
        # 1 a = 1; b = 0; cin = 1;
        # 1 a = 1; b = 1; cin = 0; 
        # 1 a = 1; b = 1; cin = 1;
    end

  wire out;
  wire sum;
//  adder(Cout, Sum, A, B, Cin);
  adder A (out, sum, a, b, cin);

  initial
        //tabela verdade
     $monitor("A: %h B: %h Cin: %h Sum: %h Cout: %h", a, b, cin, sum, out);
endmodule // test

test.vcd
$date
	Thu Oct 09 22:31:43 2014
$end
$version
	Icarus Verilog
$end
$timescale
	1s
$end
$scope module test $end
$var wire 1 ! out $end
$var wire 1 " sum $end
$var reg 1 # a $end
$var reg 1 $ b $end
$var reg 1 % cin $end
$scope module A $end
$var wire 1 & A $end
$var wire 1 ' B $end
$var wire 1 ( Cin $end
$var wire 1 ! Cout $end
$var wire 1 " Sum $end
$var wire 1 ) i1_out $end
$var wire 1 * i2_out $end
$var wire 1 + j1_out $end
$upscope $end
$upscope $end
$enddefinitions $end
#0
$dumpvars
0+
0*
0)
0(
0'
0&
0%
0$
0#
0"
0!
$end
#2
1"
1%
1(
#3
1*
0%
0(
1$
1'
#4
1!
1+
0"
1%
1(
#5
0!
0+
1"
0%
0(
0$
0'
1#
1&
#6
1!
1+
0"
1%
1(
#7
0+
1)
0*
0%
0(
1$
1'
#8
1"
1%
1(
